rnnt/__init__.py
rnnt/rnnt.py
rnnt-0.0.5.dist-info/LICENSE
rnnt-0.0.5.dist-info/METADATA
rnnt-0.0.5.dist-info/WHEEL
rnnt-0.0.5.dist-info/top_level.txt
rnnt-0.0.5.dist-info/RECORD
